yaplotlib.py
yaplotlib-0.1.3.dist-info/METADATA
yaplotlib-0.1.3.dist-info/WHEEL
yaplotlib-0.1.3.dist-info/RECORD
