Metadata-Version: 2.1
Name: yaplotlib
Version: 0.1.3
Summary: A tiny library to generate Yaplot file.
License: MIT
Author: vitroid
Author-email: vitroid@gmail.com
Requires-Python: >=3.11,<4.0
Classifier: License :: OSI Approved :: MIT License
Classifier: Programming Language :: Python :: 3
Classifier: Programming Language :: Python :: 3.11
Classifier: Programming Language :: Python :: 3.12
